singular_bug_tracker/__init__.py
singular_bug_tracker/bug_tracker.py
singular_bug_tracker/templates/traceback.html
singular_bug_tracker-0.0.5.dist-info/METADATA
singular_bug_tracker-0.0.5.dist-info/WHEEL
singular_bug_tracker-0.0.5.dist-info/top_level.txt
singular_bug_tracker-0.0.5.dist-info/RECORD
