Metadata-Version: 2.1
Name: singular-bug-tracker
Version: 0.0.5
Summary: Bug tracker
Home-page: https://lucas@bitbucket.org/singular-dev/bug_tracker.git
Author: Singular Sistemas
Author-email: ivan@singular.inf.br
License: UNKNOWN
Platform: UNKNOWN
Requires-Python: >=3.6
Requires-Dist: django
